{"type":"node_created","timestamp":"2026-05-17T10:30:08.521151647Z","node":{"id":"1.4.16","type":"claim","statement":"MAT-HET-TENSOR-N-001: For any natural number N and finite dependent families of fine and coarse coordinate index types, if each local complex matrix E_i:fine_i-\u003ecoarse_i satisfies E_i^*E_i=I, then the recursively ordered heterogeneous Kronecker tensor product of the E_i is an isometry. Moreover, if U is any finite unitary matrix on the resulting fine tensor-product coordinate space, then U times this heterogeneous tensor product is also an isometry. Lean proves this generic arbitrary-N finite-matrix theorem in Formalisation/LinearAlgebra/HeterogeneousTensor.lean by induction from the validated two-factor Kronecker isometry theorem and the validated unitary dressing theorem; Julia and WolframScript check representative four-factor heterogeneous examples with a nontrivial reversal permutation unitary. This is only finite coordinate matrix algebra for an ordered recursive tensor index; it does not construct categorical tensor products, canonical associators, ordered partition maps, local maps from fusion-category data, or the physical RG dressing unitary.","inference":"assumption","workflow_state":"available","epistemic_state":"pending","taint_state":"unresolved","content_hash":"0d06af673442b2f318e8b3ca1fd1c4fde965e5e02542d10c77c488dd59040f42","created":"2026-05-17T10:30:08.521146605Z","claimed_at":"0001-01-01T00:00:00Z"}}